[
    {
        "path":"/",
        "page":"home",
        "sectionRoot":true,
        "component":"home",
        "componentOptions":null,
        "redirect":{
            "enabled":false,
            "path":""
        }
    },
    {
        "path":"/examples/*",
        "page":"examples",
        "sectionRoot":false,
        "component":"gallery",
        "componentOptions":null,
        "redirect":{
            "enabled":false,
            "path":""
        }
    },
    {
        "path":"*",
        "page":"notFound",
        "sectionRoot":false,
        "component":"page",
        "componentOptions":null,
        "redirect":{
            "enabled":false,
            "path":""
        }
    }
]
